{".class":"MypyFile","_fullname":"google.ai.generativelanguage_v1beta.types.safety","future_import_flags":["annotations"],"is_partial_stub_package":false,"is_stub":false,"names":{".class":"SymbolTable","ContentFilter":{".class":"SymbolTableNode","kind":"Gdef","module_public":false,"node":{".class":"TypeInfo","_promote":[],"abstract_attributes":[],"alt_promote":null,"bases":["builtins.object"],"dataclass_transform_spec":null,"declared_metaclass":null,"defn":{".class":"ClassDef","fullname":"google.ai.generativelanguage_v1beta.types.safety.ContentFilter","name":"ContentFilter","type_vars":[]},"deletable_attributes":[],"deprecated":null,"flags":["fallback_to_any"],"fullname":"google.ai.generativelanguage_v1beta.types.safety.ContentFilter","has_param_spec_type":false,"metaclass_type":null,"metadata":{},"module_name":"google.ai.generativelanguage_v1beta.types.safety","mro":["google.ai.generativelanguage_v1beta.types.safety.ContentFilter","builtins.object"],"names":{".class":"SymbolTable","BlockedReason":{".class":"SymbolTableNode","kind":"Mdef","node":{".class":"TypeInfo","_promote":[],"abstract_attributes":[],"alt_promote":null,"bases":["builtins.object"],"dataclass_transform_spec":null,"declared_metaclass":null,"defn":{".class":"ClassDef","fullname":"google.ai.generativelanguage_v1beta.types.safety.ContentFilter.BlockedReason","name":"BlockedReason","type_vars":[]},"deletable_attributes":[],"deprecated":null,"flags":["fallback_to_any"],"fullname":"google.ai.generativelanguage_v1beta.types.safety.ContentFilter.BlockedReason","has_param_spec_type":false,"metaclass_type":null,"metadata":{},"module_name":"google.ai.generativelanguage_v1beta.types.safety","mro":["google.ai.generativelanguage_v1beta.types.safety.ContentFilter.BlockedReason","builtins.object"],"names":{".class":"SymbolTable","BLOCKED_REASON_UNSPECIFIED":{".class":"SymbolTableNode","kind":"Mdef","node":{".class":"Var","flags":["is_initialized_in_class","is_ready","is_inferred","has_explicit_value"],"fullname":"google.ai.generativelanguage_v1beta.types.safety.ContentFilter.BlockedReason.BLOCKED_REASON_UNSPECIFIED","name":"BLOCKED_REASON_UNSPECIFIED","type":"builtins.int"}},"OTHER":{".class":"SymbolTableNode","kind":"Mdef","node":{".class":"Var","flags":["is_initialized_in_class","is_ready","is_inferred","has_explicit_value"],"fullname":"google.ai.generativelanguage_v1beta.types.safety.ContentFilter.BlockedReason.OTHER","name":"OTHER","type":"builtins.int"}},"SAFETY":{".class":"SymbolTableNode","kind":"Mdef","node":{".class":"Var","flags":["is_initialized_in_class","is_ready","is_inferred","has_explicit_value"],"fullname":"google.ai.generativelanguage_v1beta.types.safety.ContentFilter.BlockedReason.SAFETY","name":"SAFETY","type":"builtins.int"}}},"self_type":{".class":"TypeVarType","default":{".class":"AnyType","missing_import_name":null,"source_any":null,"type_of_any":4},"fullname":"google.ai.generativelanguage_v1beta.types.safety.ContentFilter.BlockedReason.Self","id":0,"name":"Self","namespace":"","upper_bound":"google.ai.generativelanguage_v1beta.types.safety.ContentFilter.BlockedReason","values":[],"variance":0},"slots":null,"tuple_type":null,"type_vars":[],"typeddict_type":null}},"message":{".class":"SymbolTableNode","kind":"Mdef","node":{".class":"Var","flags":["is_initialized_in_class","is_ready","has_explicit_value"],"fullname":"google.ai.generativelanguage_v1beta.types.safety.ContentFilter.message","name":"message","type":"builtins.str"}},"reason":{".class":"SymbolTableNode","kind":"Mdef","node":{".class":"Var","flags":["is_initialized_in_class","is_ready","has_explicit_value"],"fullname":"google.ai.generativelanguage_v1beta.types.safety.ContentFilter.reason","name":"reason","type":"google.ai.generativelanguage_v1beta.types.safety.ContentFilter.BlockedReason"}}},"self_type":{".class":"TypeVarType","default":{".class":"AnyType","missing_import_name":null,"source_any":null,"type_of_any":4},"fullname":"google.ai.generativelanguage_v1beta.types.safety.ContentFilter.Self","id":0,"name":"Self","namespace":"","upper_bound":"google.ai.generativelanguage_v1beta.types.safety.ContentFilter","values":[],"variance":0},"slots":null,"tuple_type":null,"type_vars":[],"typeddict_type":null}},"HarmCategory":{".class":"SymbolTableNode","kind":"Gdef","module_public":false,"node":{".class":"TypeInfo","_promote":[],"abstract_attributes":[],"alt_promote":null,"bases":["builtins.object"],"dataclass_transform_spec":null,"declared_metaclass":null,"defn":{".class":"ClassDef","fullname":"google.ai.generativelanguage_v1beta.types.safety.HarmCategory","name":"HarmCategory","type_vars":[]},"deletable_attributes":[],"deprecated":null,"flags":["fallback_to_any"],"fullname":"google.ai.generativelanguage_v1beta.types.safety.HarmCategory","has_param_spec_type":false,"metaclass_type":null,"metadata":{},"module_name":"google.ai.generativelanguage_v1beta.types.safety","mro":["google.ai.generativelanguage_v1beta.types.safety.HarmCategory","builtins.object"],"names":{".class":"SymbolTable","HARM_CATEGORY_CIVIC_INTEGRITY":{".class":"SymbolTableNode","kind":"Mdef","node":{".class":"Var","flags":["is_initialized_in_class","is_ready","is_inferred","has_explicit_value"],"fullname":"google.ai.generativelanguage_v1beta.types.safety.HarmCategory.HARM_CATEGORY_CIVIC_INTEGRITY","name":"HARM_CATEGORY_CIVIC_INTEGRITY","type":"builtins.int"}},"HARM_CATEGORY_DANGEROUS":{".class":"SymbolTableNode","kind":"Mdef","node":{".class":"Var","flags":["is_initialized_in_class","is_ready","is_inferred","has_explicit_value"],"fullname":"google.ai.generativelanguage_v1beta.types.safety.HarmCategory.HARM_CATEGORY_DANGEROUS","name":"HARM_CATEGORY_DANGEROUS","type":"builtins.int"}},"HARM_CATEGORY_DANGEROUS_CONTENT":{".class":"SymbolTableNode","kind":"Mdef","node":{".class":"Var","flags":["is_initialized_in_class","is_ready","is_inferred","has_explicit_value"],"fullname":"google.ai.generativelanguage_v1beta.types.safety.HarmCategory.HARM_CATEGORY_DANGEROUS_CONTENT","name":"HARM_CATEGORY_DANGEROUS_CONTENT","type":"builtins.int"}},"HARM_CATEGORY_DEROGATORY":{".class":"SymbolTableNode","kind":"Mdef","node":{".class":"Var","flags":["is_initialized_in_class","is_ready","is_inferred","has_explicit_value"],"fullname":"google.ai.generativelanguage_v1beta.types.safety.HarmCategory.HARM_CATEGORY_DEROGATORY","name":"HARM_CATEGORY_DEROGATORY","type":"builtins.int"}},"HARM_CATEGORY_HARASSMENT":{".class":"SymbolTableNode","kind":"Mdef","node":{".class":"Var","flags":["is_initialized_in_class","is_ready","is_inferred","has_explicit_value"],"fullname":"google.ai.generativelanguage_v1beta.types.safety.HarmCategory.HARM_CATEGORY_HARASSMENT","name":"HARM_CATEGORY_HARASSMENT","type":"builtins.int"}},"HARM_CATEGORY_HATE_SPEECH":{".class":"SymbolTableNode","kind":"Mdef","node":{".class":"Var","flags":["is_initialized_in_class","is_ready","is_inferred","has_explicit_value"],"fullname":"google.ai.generativelanguage_v1beta.types.safety.HarmCategory.HARM_CATEGORY_HATE_SPEECH","name":"HARM_CATEGORY_HATE_SPEECH","type":"builtins.int"}},"HARM_CATEGORY_MEDICAL":{".class":"SymbolTableNode","kind":"Mdef","node":{".class":"Var","flags":["is_initialized_in_class","is_ready","is_inferred","has_explicit_value"],"fullname":"google.ai.generativelanguage_v1beta.types.safety.HarmCategory.HARM_CATEGORY_MEDICAL","name":"HARM_CATEGORY_MEDICAL","type":"builtins.int"}},"HARM_CATEGORY_SEXUAL":{".class":"SymbolTableNode","kind":"Mdef","node":{".class":"Var","flags":["is_initialized_in_class","is_ready","is_inferred","has_explicit_value"],"fullname":"google.ai.generativelanguage_v1beta.types.safety.HarmCategory.HARM_CATEGORY_SEXUAL","name":"HARM_CATEGORY_SEXUAL","type":"builtins.int"}},"HARM_CATEGORY_SEXUALLY_EXPLICIT":{".class":"SymbolTableNode","kind":"Mdef","node":{".class":"Var","flags":["is_initialized_in_class","is_ready","is_inferred","has_explicit_value"],"fullname":"google.ai.generativelanguage_v1beta.types.safety.HarmCategory.HARM_CATEGORY_SEXUALLY_EXPLICIT","name":"HARM_CATEGORY_SEXUALLY_EXPLICIT","type":"builtins.int"}},"HARM_CATEGORY_TOXICITY":{".class":"SymbolTableNode","kind":"Mdef","node":{".class":"Var","flags":["is_initialized_in_class","is_ready","is_inferred","has_explicit_value"],"fullname":"google.ai.generativelanguage_v1beta.types.safety.HarmCategory.HARM_CATEGORY_TOXICITY","name":"HARM_CATEGORY_TOXICITY","type":"builtins.int"}},"HARM_CATEGORY_UNSPECIFIED":{".class":"SymbolTableNode","kind":"Mdef","node":{".class":"Var","flags":["is_initialized_in_class","is_ready","is_inferred","has_explicit_value"],"fullname":"google.ai.generativelanguage_v1beta.types.safety.HarmCategory.HARM_CATEGORY_UNSPECIFIED","name":"HARM_CATEGORY_UNSPECIFIED","type":"builtins.int"}},"HARM_CATEGORY_VIOLENCE":{".class":"SymbolTableNode","kind":"Mdef","node":{".class":"Var","flags":["is_initialized_in_class","is_ready","is_inferred","has_explicit_value"],"fullname":"google.ai.generativelanguage_v1beta.types.safety.HarmCategory.HARM_CATEGORY_VIOLENCE","name":"HARM_CATEGORY_VIOLENCE","type":"builtins.int"}}},"self_type":{".class":"TypeVarType","default":{".class":"AnyType","missing_import_name":null,"source_any":null,"type_of_any":4},"fullname":"google.ai.generativelanguage_v1beta.types.safety.HarmCategory.Self","id":0,"name":"Self","namespace":"","upper_bound":"google.ai.generativelanguage_v1beta.types.safety.HarmCategory","values":[],"variance":0},"slots":null,"tuple_type":null,"type_vars":[],"typeddict_type":null}},"MutableMapping":{".class":"SymbolTableNode","cross_ref":"typing.MutableMapping","kind":"Gdef","module_public":false},"MutableSequence":{".class":"SymbolTableNode","cross_ref":"typing.MutableSequence","kind":"Gdef","module_public":false},"SafetyFeedback":{".class":"SymbolTableNode","kind":"Gdef","module_public":false,"node":{".class":"TypeInfo","_promote":[],"abstract_attributes":[],"alt_promote":null,"bases":["builtins.object"],"dataclass_transform_spec":null,"declared_metaclass":null,"defn":{".class":"ClassDef","fullname":"google.ai.generativelanguage_v1beta.types.safety.SafetyFeedback","name":"SafetyFeedback","type_vars":[]},"deletable_attributes":[],"deprecated":null,"flags":["fallback_to_any"],"fullname":"google.ai.generativelanguage_v1beta.types.safety.SafetyFeedback","has_param_spec_type":false,"metaclass_type":null,"metadata":{},"module_name":"google.ai.generativelanguage_v1beta.types.safety","mro":["google.ai.generativelanguage_v1beta.types.safety.SafetyFeedback","builtins.object"],"names":{".class":"SymbolTable","rating":{".class":"SymbolTableNode","kind":"Mdef","node":{".class":"Var","flags":["is_initialized_in_class","is_ready","has_explicit_value"],"fullname":"google.ai.generativelanguage_v1beta.types.safety.SafetyFeedback.rating","name":"rating","type":"google.ai.generativelanguage_v1beta.types.safety.SafetyRating"}},"setting":{".class":"SymbolTableNode","kind":"Mdef","node":{".class":"Var","flags":["is_initialized_in_class","is_ready","has_explicit_value"],"fullname":"google.ai.generativelanguage_v1beta.types.safety.SafetyFeedback.setting","name":"setting","type":"google.ai.generativelanguage_v1beta.types.safety.SafetySetting"}}},"self_type":{".class":"TypeVarType","default":{".class":"AnyType","missing_import_name":null,"source_any":null,"type_of_any":4},"fullname":"google.ai.generativelanguage_v1beta.types.safety.SafetyFeedback.Self","id":0,"name":"Self","namespace":"","upper_bound":"google.ai.generativelanguage_v1beta.types.safety.SafetyFeedback","values":[],"variance":0},"slots":null,"tuple_type":null,"type_vars":[],"typeddict_type":null}},"SafetyRating":{".class":"SymbolTableNode","kind":"Gdef","module_public":false,"node":{".class":"TypeInfo","_promote":[],"abstract_attributes":[],"alt_promote":null,"bases":["builtins.object"],"dataclass_transform_spec":null,"declared_metaclass":null,"defn":{".class":"ClassDef","fullname":"google.ai.generativelanguage_v1beta.types.safety.SafetyRating","name":"SafetyRating","type_vars":[]},"deletable_attributes":[],"deprecated":null,"flags":["fallback_to_any"],"fullname":"google.ai.generativelanguage_v1beta.types.safety.SafetyRating","has_param_spec_type":false,"metaclass_type":null,"metadata":{},"module_name":"google.ai.generativelanguage_v1beta.types.safety","mro":["google.ai.generativelanguage_v1beta.types.safety.SafetyRating","builtins.object"],"names":{".class":"SymbolTable","HarmProbability":{".class":"SymbolTableNode","kind":"Mdef","node":{".class":"TypeInfo","_promote":[],"abstract_attributes":[],"alt_promote":null,"bases":["builtins.object"],"dataclass_transform_spec":null,"declared_metaclass":null,"defn":{".class":"ClassDef","fullname":"google.ai.generativelanguage_v1beta.types.safety.SafetyRating.HarmProbability","name":"HarmProbability","type_vars":[]},"deletable_attributes":[],"deprecated":null,"flags":["fallback_to_any"],"fullname":"google.ai.generativelanguage_v1beta.types.safety.SafetyRating.HarmProbability","has_param_spec_type":false,"metaclass_type":null,"metadata":{},"module_name":"google.ai.generativelanguage_v1beta.types.safety","mro":["google.ai.generativelanguage_v1beta.types.safety.SafetyRating.HarmProbability","builtins.object"],"names":{".class":"SymbolTable","HARM_PROBABILITY_UNSPECIFIED":{".class":"SymbolTableNode","kind":"Mdef","node":{".class":"Var","flags":["is_initialized_in_class","is_ready","is_inferred","has_explicit_value"],"fullname":"google.ai.generativelanguage_v1beta.types.safety.SafetyRating.HarmProbability.HARM_PROBABILITY_UNSPECIFIED","name":"HARM_PROBABILITY_UNSPECIFIED","type":"builtins.int"}},"HIGH":{".class":"SymbolTableNode","kind":"Mdef","node":{".class":"Var","flags":["is_initialized_in_class","is_ready","is_inferred","has_explicit_value"],"fullname":"google.ai.generativelanguage_v1beta.types.safety.SafetyRating.HarmProbability.HIGH","name":"HIGH","type":"builtins.int"}},"LOW":{".class":"SymbolTableNode","kind":"Mdef","node":{".class":"Var","flags":["is_initialized_in_class","is_ready","is_inferred","has_explicit_value"],"fullname":"google.ai.generativelanguage_v1beta.types.safety.SafetyRating.HarmProbability.LOW","name":"LOW","type":"builtins.int"}},"MEDIUM":{".class":"SymbolTableNode","kind":"Mdef","node":{".class":"Var","flags":["is_initialized_in_class","is_ready","is_inferred","has_explicit_value"],"fullname":"google.ai.generativelanguage_v1beta.types.safety.SafetyRating.HarmProbability.MEDIUM","name":"MEDIUM","type":"builtins.int"}},"NEGLIGIBLE":{".class":"SymbolTableNode","kind":"Mdef","node":{".class":"Var","flags":["is_initialized_in_class","is_ready","is_inferred","has_explicit_value"],"fullname":"google.ai.generativelanguage_v1beta.types.safety.SafetyRating.HarmProbability.NEGLIGIBLE","name":"NEGLIGIBLE","type":"builtins.int"}}},"self_type":{".class":"TypeVarType","default":{".class":"AnyType","missing_import_name":null,"source_any":null,"type_of_any":4},"fullname":"google.ai.generativelanguage_v1beta.types.safety.SafetyRating.HarmProbability.Self","id":0,"name":"Self","namespace":"","upper_bound":"google.ai.generativelanguage_v1beta.types.safety.SafetyRating.HarmProbability","values":[],"variance":0},"slots":null,"tuple_type":null,"type_vars":[],"typeddict_type":null}},"blocked":{".class":"SymbolTableNode","kind":"Mdef","node":{".class":"Var","flags":["is_initialized_in_class","is_ready","has_explicit_value"],"fullname":"google.ai.generativelanguage_v1beta.types.safety.SafetyRating.blocked","name":"blocked","type":"builtins.bool"}},"category":{".class":"SymbolTableNode","kind":"Mdef","node":{".class":"Var","flags":["is_initialized_in_class","is_ready","has_explicit_value"],"fullname":"google.ai.generativelanguage_v1beta.types.safety.SafetyRating.category","name":"category","type":"google.ai.generativelanguage_v1beta.types.safety.HarmCategory"}},"probability":{".class":"SymbolTableNode","kind":"Mdef","node":{".class":"Var","flags":["is_initialized_in_class","is_ready","has_explicit_value"],"fullname":"google.ai.generativelanguage_v1beta.types.safety.SafetyRating.probability","name":"probability","type":"google.ai.generativelanguage_v1beta.types.safety.SafetyRating.HarmProbability"}}},"self_type":{".class":"TypeVarType","default":{".class":"AnyType","missing_import_name":null,"source_any":null,"type_of_any":4},"fullname":"google.ai.generativelanguage_v1beta.types.safety.SafetyRating.Self","id":0,"name":"Self","namespace":"","upper_bound":"google.ai.generativelanguage_v1beta.types.safety.SafetyRating","values":[],"variance":0},"slots":null,"tuple_type":null,"type_vars":[],"typeddict_type":null}},"SafetySetting":{".class":"SymbolTableNode","kind":"Gdef","module_public":false,"node":{".class":"TypeInfo","_promote":[],"abstract_attributes":[],"alt_promote":null,"bases":["builtins.object"],"dataclass_transform_spec":null,"declared_metaclass":null,"defn":{".class":"ClassDef","fullname":"google.ai.generativelanguage_v1beta.types.safety.SafetySetting","name":"SafetySetting","type_vars":[]},"deletable_attributes":[],"deprecated":null,"flags":["fallback_to_any"],"fullname":"google.ai.generativelanguage_v1beta.types.safety.SafetySetting","has_param_spec_type":false,"metaclass_type":null,"metadata":{},"module_name":"google.ai.generativelanguage_v1beta.types.safety","mro":["google.ai.generativelanguage_v1beta.types.safety.SafetySetting","builtins.object"],"names":{".class":"SymbolTable","HarmBlockThreshold":{".class":"SymbolTableNode","kind":"Mdef","node":{".class":"TypeInfo","_promote":[],"abstract_attributes":[],"alt_promote":null,"bases":["builtins.object"],"dataclass_transform_spec":null,"declared_metaclass":null,"defn":{".class":"ClassDef","fullname":"google.ai.generativelanguage_v1beta.types.safety.SafetySetting.HarmBlockThreshold","name":"HarmBlockThreshold","type_vars":[]},"deletable_attributes":[],"deprecated":null,"flags":["fallback_to_any"],"fullname":"google.ai.generativelanguage_v1beta.types.safety.SafetySetting.HarmBlockThreshold","has_param_spec_type":false,"metaclass_type":null,"metadata":{},"module_name":"google.ai.generativelanguage_v1beta.types.safety","mro":["google.ai.generativelanguage_v1beta.types.safety.SafetySetting.HarmBlockThreshold","builtins.object"],"names":{".class":"SymbolTable","BLOCK_LOW_AND_ABOVE":{".class":"SymbolTableNode","kind":"Mdef","node":{".class":"Var","flags":["is_initialized_in_class","is_ready","is_inferred","has_explicit_value"],"fullname":"google.ai.generativelanguage_v1beta.types.safety.SafetySetting.HarmBlockThreshold.BLOCK_LOW_AND_ABOVE","name":"BLOCK_LOW_AND_ABOVE","type":"builtins.int"}},"BLOCK_MEDIUM_AND_ABOVE":{".class":"SymbolTableNode","kind":"Mdef","node":{".class":"Var","flags":["is_initialized_in_class","is_ready","is_inferred","has_explicit_value"],"fullname":"google.ai.generativelanguage_v1beta.types.safety.SafetySetting.HarmBlockThreshold.BLOCK_MEDIUM_AND_ABOVE","name":"BLOCK_MEDIUM_AND_ABOVE","type":"builtins.int"}},"BLOCK_NONE":{".class":"SymbolTableNode","kind":"Mdef","node":{".class":"Var","flags":["is_initialized_in_class","is_ready","is_inferred","has_explicit_value"],"fullname":"google.ai.generativelanguage_v1beta.types.safety.SafetySetting.HarmBlockThreshold.BLOCK_NONE","name":"BLOCK_NONE","type":"builtins.int"}},"BLOCK_ONLY_HIGH":{".class":"SymbolTableNode","kind":"Mdef","node":{".class":"Var","flags":["is_initialized_in_class","is_ready","is_inferred","has_explicit_value"],"fullname":"google.ai.generativelanguage_v1beta.types.safety.SafetySetting.HarmBlockThreshold.BLOCK_ONLY_HIGH","name":"BLOCK_ONLY_HIGH","type":"builtins.int"}},"HARM_BLOCK_THRESHOLD_UNSPECIFIED":{".class":"SymbolTableNode","kind":"Mdef","node":{".class":"Var","flags":["is_initialized_in_class","is_ready","is_inferred","has_explicit_value"],"fullname":"google.ai.generativelanguage_v1beta.types.safety.SafetySetting.HarmBlockThreshold.HARM_BLOCK_THRESHOLD_UNSPECIFIED","name":"HARM_BLOCK_THRESHOLD_UNSPECIFIED","type":"builtins.int"}},"OFF":{".class":"SymbolTableNode","kind":"Mdef","node":{".class":"Var","flags":["is_initialized_in_class","is_ready","is_inferred","has_explicit_value"],"fullname":"google.ai.generativelanguage_v1beta.types.safety.SafetySetting.HarmBlockThreshold.OFF","name":"OFF","type":"builtins.int"}}},"self_type":{".class":"TypeVarType","default":{".class":"AnyType","missing_import_name":null,"source_any":null,"type_of_any":4},"fullname":"google.ai.generativelanguage_v1beta.types.safety.SafetySetting.HarmBlockThreshold.Self","id":0,"name":"Self","namespace":"","upper_bound":"google.ai.generativelanguage_v1beta.types.safety.SafetySetting.HarmBlockThreshold","values":[],"variance":0},"slots":null,"tuple_type":null,"type_vars":[],"typeddict_type":null}},"category":{".class":"SymbolTableNode","kind":"Mdef","node":{".class":"Var","flags":["is_initialized_in_class","is_ready","has_explicit_value"],"fullname":"google.ai.generativelanguage_v1beta.types.safety.SafetySetting.category","name":"category","type":"google.ai.generativelanguage_v1beta.types.safety.HarmCategory"}},"threshold":{".class":"SymbolTableNode","kind":"Mdef","node":{".class":"Var","flags":["is_initialized_in_class","is_ready","has_explicit_value"],"fullname":"google.ai.generativelanguage_v1beta.types.safety.SafetySetting.threshold","name":"threshold","type":"google.ai.generativelanguage_v1beta.types.safety.SafetySetting.HarmBlockThreshold"}}},"self_type":{".class":"TypeVarType","default":{".class":"AnyType","missing_import_name":null,"source_any":null,"type_of_any":4},"fullname":"google.ai.generativelanguage_v1beta.types.safety.SafetySetting.Self","id":0,"name":"Self","namespace":"","upper_bound":"google.ai.generativelanguage_v1beta.types.safety.SafetySetting","values":[],"variance":0},"slots":null,"tuple_type":null,"type_vars":[],"typeddict_type":null}},"__all__":{".class":"SymbolTableNode","kind":"Gdef","module_public":false,"node":{".class":"Var","flags":["is_inferred","has_explicit_value"],"fullname":"google.ai.generativelanguage_v1beta.types.safety.__all__","name":"__all__","type":{".class":"Instance","args":[{".class":"AnyType","missing_import_name":"google.ai.generativelanguage_v1beta.types.safety.proto","source_any":{".class":"AnyType","missing_import_name":"google.ai.generativelanguage_v1beta.types.safety.proto","source_any":null,"type_of_any":3},"type_of_any":7}],"extra_attrs":null,"type_ref":"builtins.tuple"}}},"__annotations__":{".class":"SymbolTableNode","kind":"Gdef","module_public":false,"node":{".class":"Var","flags":["is_ready"],"fullname":"google.ai.generativelanguage_v1beta.types.safety.__annotations__","name":"__annotations__","type":{".class":"Instance","args":["builtins.str",{".class":"AnyType","missing_import_name":null,"source_any":null,"type_of_any":6}],"extra_attrs":null,"type_ref":"builtins.dict"}}},"__doc__":{".class":"SymbolTableNode","kind":"Gdef","module_public":false,"node":{".class":"Var","flags":["is_ready"],"fullname":"google.ai.generativelanguage_v1beta.types.safety.__doc__","name":"__doc__","type":"builtins.str"}},"__file__":{".class":"SymbolTableNode","kind":"Gdef","module_public":false,"node":{".class":"Var","flags":["is_ready"],"fullname":"google.ai.generativelanguage_v1beta.types.safety.__file__","name":"__file__","type":"builtins.str"}},"__name__":{".class":"SymbolTableNode","kind":"Gdef","module_public":false,"node":{".class":"Var","flags":["is_ready"],"fullname":"google.ai.generativelanguage_v1beta.types.safety.__name__","name":"__name__","type":"builtins.str"}},"__package__":{".class":"SymbolTableNode","kind":"Gdef","module_public":false,"node":{".class":"Var","flags":["is_ready"],"fullname":"google.ai.generativelanguage_v1beta.types.safety.__package__","name":"__package__","type":"builtins.str"}},"__protobuf__":{".class":"SymbolTableNode","kind":"Gdef","module_public":false,"node":{".class":"Var","flags":["is_inferred","has_explicit_value"],"fullname":"google.ai.generativelanguage_v1beta.types.safety.__protobuf__","name":"__protobuf__","type":{".class":"AnyType","missing_import_name":"google.ai.generativelanguage_v1beta.types.safety.proto","source_any":{".class":"AnyType","missing_import_name":"google.ai.generativelanguage_v1beta.types.safety.proto","source_any":null,"type_of_any":3},"type_of_any":7}}},"__spec__":{".class":"SymbolTableNode","kind":"Gdef","module_public":false,"node":{".class":"Var","flags":["is_ready"],"fullname":"google.ai.generativelanguage_v1beta.types.safety.__spec__","name":"__spec__","type":"_frozen_importlib.ModuleSpec"}},"annotations":{".class":"SymbolTableNode","cross_ref":"__future__.annotations","kind":"Gdef","module_public":false},"proto":{".class":"SymbolTableNode","kind":"Gdef","module_public":false,"node":{".class":"Var","flags":["is_suppressed_import","is_ready","is_inferred"],"fullname":"google.ai.generativelanguage_v1beta.types.safety.proto","name":"proto","type":{".class":"AnyType","missing_import_name":"google.ai.generativelanguage_v1beta.types.safety.proto","source_any":null,"type_of_any":3}}}},"path":"C:\\Users\\user\\AppData\\Local\\Packages\\PythonSoftwareFoundation.Python.3.12_qbz5n2kfra8p0\\LocalCache\\local-packages\\Python312\\site-packages\\google\\ai\\generativelanguage_v1beta\\types\\safety.py"}