{".class":"MypyFile","_fullname":"google.generativeai.protos","future_import_flags":[],"is_partial_stub_package":false,"is_stub":false,"names":{".class":"SymbolTable","AttributionSourceId":{".class":"SymbolTableNode","cross_ref":"google.ai.generativelanguage_v1beta.types.generative_service.AttributionSourceId","kind":"Gdef","module_public":false},"BatchCreateChunksRequest":{".class":"SymbolTableNode","cross_ref":"google.ai.generativelanguage_v1beta.types.retriever_service.BatchCreateChunksRequest","kind":"Gdef","module_public":false},"BatchCreateChunksResponse":{".class":"SymbolTableNode","cross_ref":"google.ai.generativelanguage_v1beta.types.retriever_service.BatchCreateChunksResponse","kind":"Gdef","module_public":false},"BatchDeleteChunksRequest":{".class":"SymbolTableNode","cross_ref":"google.ai.generativelanguage_v1beta.types.retriever_service.BatchDeleteChunksRequest","kind":"Gdef","module_public":false},"BatchEmbedContentsRequest":{".class":"SymbolTableNode","cross_ref":"google.ai.generativelanguage_v1beta.types.generative_service.BatchEmbedContentsRequest","kind":"Gdef","module_public":false},"BatchEmbedContentsResponse":{".class":"SymbolTableNode","cross_ref":"google.ai.generativelanguage_v1beta.types.generative_service.BatchEmbedContentsResponse","kind":"Gdef","module_public":false},"BatchEmbedTextRequest":{".class":"SymbolTableNode","cross_ref":"google.ai.generativelanguage_v1beta.types.text_service.BatchEmbedTextRequest","kind":"Gdef","module_public":false},"BatchEmbedTextResponse":{".class":"SymbolTableNode","cross_ref":"google.ai.generativelanguage_v1beta.types.text_service.BatchEmbedTextResponse","kind":"Gdef","module_public":false},"BatchUpdateChunksRequest":{".class":"SymbolTableNode","cross_ref":"google.ai.generativelanguage_v1beta.types.retriever_service.BatchUpdateChunksRequest","kind":"Gdef","module_public":false},"BatchUpdateChunksResponse":{".class":"SymbolTableNode","cross_ref":"google.ai.generativelanguage_v1beta.types.retriever_service.BatchUpdateChunksResponse","kind":"Gdef","module_public":false},"Blob":{".class":"SymbolTableNode","cross_ref":"google.ai.generativelanguage_v1beta.types.content.Blob","kind":"Gdef","module_public":false},"CachedContent":{".class":"SymbolTableNode","cross_ref":"google.ai.generativelanguage_v1beta.types.cached_content.CachedContent","kind":"Gdef","module_public":false},"Candidate":{".class":"SymbolTableNode","cross_ref":"google.ai.generativelanguage_v1beta.types.generative_service.Candidate","kind":"Gdef","module_public":false},"Chunk":{".class":"SymbolTableNode","cross_ref":"google.ai.generativelanguage_v1beta.types.retriever.Chunk","kind":"Gdef","module_public":false},"ChunkData":{".class":"SymbolTableNode","cross_ref":"google.ai.generativelanguage_v1beta.types.retriever.ChunkData","kind":"Gdef","module_public":false},"CitationMetadata":{".class":"SymbolTableNode","cross_ref":"google.ai.generativelanguage_v1beta.types.citation.CitationMetadata","kind":"Gdef","module_public":false},"CitationSource":{".class":"SymbolTableNode","cross_ref":"google.ai.generativelanguage_v1beta.types.citation.CitationSource","kind":"Gdef","module_public":false},"CodeExecution":{".class":"SymbolTableNode","cross_ref":"google.ai.generativelanguage_v1beta.types.content.CodeExecution","kind":"Gdef","module_public":false},"CodeExecutionResult":{".class":"SymbolTableNode","cross_ref":"google.ai.generativelanguage_v1beta.types.content.CodeExecutionResult","kind":"Gdef","module_public":false},"Condition":{".class":"SymbolTableNode","cross_ref":"google.ai.generativelanguage_v1beta.types.retriever.Condition","kind":"Gdef","module_public":false},"Content":{".class":"SymbolTableNode","cross_ref":"google.ai.generativelanguage_v1beta.types.content.Content","kind":"Gdef","module_public":false},"ContentEmbedding":{".class":"SymbolTableNode","cross_ref":"google.ai.generativelanguage_v1beta.types.generative_service.ContentEmbedding","kind":"Gdef","module_public":false},"ContentFilter":{".class":"SymbolTableNode","cross_ref":"google.ai.generativelanguage_v1beta.types.safety.ContentFilter","kind":"Gdef","module_public":false},"Corpus":{".class":"SymbolTableNode","cross_ref":"google.ai.generativelanguage_v1beta.types.retriever.Corpus","kind":"Gdef","module_public":false},"CountMessageTokensRequest":{".class":"SymbolTableNode","cross_ref":"google.ai.generativelanguage_v1beta.types.discuss_service.CountMessageTokensRequest","kind":"Gdef","module_public":false},"CountMessageTokensResponse":{".class":"SymbolTableNode","cross_ref":"google.ai.generativelanguage_v1beta.types.discuss_service.CountMessageTokensResponse","kind":"Gdef","module_public":false},"CountTextTokensRequest":{".class":"SymbolTableNode","cross_ref":"google.ai.generativelanguage_v1beta.types.text_service.CountTextTokensRequest","kind":"Gdef","module_public":false},"CountTextTokensResponse":{".class":"SymbolTableNode","cross_ref":"google.ai.generativelanguage_v1beta.types.text_service.CountTextTokensResponse","kind":"Gdef","module_public":false},"CountTokensRequest":{".class":"SymbolTableNode","cross_ref":"google.ai.generativelanguage_v1beta.types.generative_service.CountTokensRequest","kind":"Gdef","module_public":false},"CountTokensResponse":{".class":"SymbolTableNode","cross_ref":"google.ai.generativelanguage_v1beta.types.generative_service.CountTokensResponse","kind":"Gdef","module_public":false},"CreateCachedContentRequest":{".class":"SymbolTableNode","cross_ref":"google.ai.generativelanguage_v1beta.types.cache_service.CreateCachedContentRequest","kind":"Gdef","module_public":false},"CreateChunkRequest":{".class":"SymbolTableNode","cross_ref":"google.ai.generativelanguage_v1beta.types.retriever_service.CreateChunkRequest","kind":"Gdef","module_public":false},"CreateCorpusRequest":{".class":"SymbolTableNode","cross_ref":"google.ai.generativelanguage_v1beta.types.retriever_service.CreateCorpusRequest","kind":"Gdef","module_public":false},"CreateDocumentRequest":{".class":"SymbolTableNode","cross_ref":"google.ai.generativelanguage_v1beta.types.retriever_service.CreateDocumentRequest","kind":"Gdef","module_public":false},"CreateFileRequest":{".class":"SymbolTableNode","cross_ref":"google.ai.generativelanguage_v1beta.types.file_service.CreateFileRequest","kind":"Gdef","module_public":false},"CreateFileResponse":{".class":"SymbolTableNode","cross_ref":"google.ai.generativelanguage_v1beta.types.file_service.CreateFileResponse","kind":"Gdef","module_public":false},"CreatePermissionRequest":{".class":"SymbolTableNode","cross_ref":"google.ai.generativelanguage_v1beta.types.permission_service.CreatePermissionRequest","kind":"Gdef","module_public":false},"CreateTunedModelMetadata":{".class":"SymbolTableNode","cross_ref":"google.ai.generativelanguage_v1beta.types.model_service.CreateTunedModelMetadata","kind":"Gdef","module_public":false},"CreateTunedModelRequest":{".class":"SymbolTableNode","cross_ref":"google.ai.generativelanguage_v1beta.types.model_service.CreateTunedModelRequest","kind":"Gdef","module_public":false},"CustomMetadata":{".class":"SymbolTableNode","cross_ref":"google.ai.generativelanguage_v1beta.types.retriever.CustomMetadata","kind":"Gdef","module_public":false},"Dataset":{".class":"SymbolTableNode","cross_ref":"google.ai.generativelanguage_v1beta.types.tuned_model.Dataset","kind":"Gdef","module_public":false},"DeleteCachedContentRequest":{".class":"SymbolTableNode","cross_ref":"google.ai.generativelanguage_v1beta.types.cache_service.DeleteCachedContentRequest","kind":"Gdef","module_public":false},"DeleteChunkRequest":{".class":"SymbolTableNode","cross_ref":"google.ai.generativelanguage_v1beta.types.retriever_service.DeleteChunkRequest","kind":"Gdef","module_public":false},"DeleteCorpusRequest":{".class":"SymbolTableNode","cross_ref":"google.ai.generativelanguage_v1beta.types.retriever_service.DeleteCorpusRequest","kind":"Gdef","module_public":false},"DeleteDocumentRequest":{".class":"SymbolTableNode","cross_ref":"google.ai.generativelanguage_v1beta.types.retriever_service.DeleteDocumentRequest","kind":"Gdef","module_public":false},"DeleteFileRequest":{".class":"SymbolTableNode","cross_ref":"google.ai.generativelanguage_v1beta.types.file_service.DeleteFileRequest","kind":"Gdef","module_public":false},"DeletePermissionRequest":{".class":"SymbolTableNode","cross_ref":"google.ai.generativelanguage_v1beta.types.permission_service.DeletePermissionRequest","kind":"Gdef","module_public":false},"DeleteTunedModelRequest":{".class":"SymbolTableNode","cross_ref":"google.ai.generativelanguage_v1beta.types.model_service.DeleteTunedModelRequest","kind":"Gdef","module_public":false},"Document":{".class":"SymbolTableNode","cross_ref":"google.ai.generativelanguage_v1beta.types.retriever.Document","kind":"Gdef","module_public":false},"DynamicRetrievalConfig":{".class":"SymbolTableNode","cross_ref":"google.ai.generativelanguage_v1beta.types.content.DynamicRetrievalConfig","kind":"Gdef","module_public":false},"EmbedContentRequest":{".class":"SymbolTableNode","cross_ref":"google.ai.generativelanguage_v1beta.types.generative_service.EmbedContentRequest","kind":"Gdef","module_public":false},"EmbedContentResponse":{".class":"SymbolTableNode","cross_ref":"google.ai.generativelanguage_v1beta.types.generative_service.EmbedContentResponse","kind":"Gdef","module_public":false},"EmbedTextRequest":{".class":"SymbolTableNode","cross_ref":"google.ai.generativelanguage_v1beta.types.text_service.EmbedTextRequest","kind":"Gdef","module_public":false},"EmbedTextResponse":{".class":"SymbolTableNode","cross_ref":"google.ai.generativelanguage_v1beta.types.text_service.EmbedTextResponse","kind":"Gdef","module_public":false},"Embedding":{".class":"SymbolTableNode","cross_ref":"google.ai.generativelanguage_v1beta.types.text_service.Embedding","kind":"Gdef","module_public":false},"Example":{".class":"SymbolTableNode","cross_ref":"google.ai.generativelanguage_v1beta.types.discuss_service.Example","kind":"Gdef","module_public":false},"ExecutableCode":{".class":"SymbolTableNode","cross_ref":"google.ai.generativelanguage_v1beta.types.content.ExecutableCode","kind":"Gdef","module_public":false},"File":{".class":"SymbolTableNode","cross_ref":"google.ai.generativelanguage_v1beta.types.file.File","kind":"Gdef","module_public":false},"FileData":{".class":"SymbolTableNode","cross_ref":"google.ai.generativelanguage_v1beta.types.content.FileData","kind":"Gdef","module_public":false},"FunctionCall":{".class":"SymbolTableNode","cross_ref":"google.ai.generativelanguage_v1beta.types.content.FunctionCall","kind":"Gdef","module_public":false},"FunctionCallingConfig":{".class":"SymbolTableNode","cross_ref":"google.ai.generativelanguage_v1beta.types.content.FunctionCallingConfig","kind":"Gdef","module_public":false},"FunctionDeclaration":{".class":"SymbolTableNode","cross_ref":"google.ai.generativelanguage_v1beta.types.content.FunctionDeclaration","kind":"Gdef","module_public":false},"FunctionResponse":{".class":"SymbolTableNode","cross_ref":"google.ai.generativelanguage_v1beta.types.content.FunctionResponse","kind":"Gdef","module_public":false},"GenerateAnswerRequest":{".class":"SymbolTableNode","cross_ref":"google.ai.generativelanguage_v1beta.types.generative_service.GenerateAnswerRequest","kind":"Gdef","module_public":false},"GenerateAnswerResponse":{".class":"SymbolTableNode","cross_ref":"google.ai.generativelanguage_v1beta.types.generative_service.GenerateAnswerResponse","kind":"Gdef","module_public":false},"GenerateContentRequest":{".class":"SymbolTableNode","cross_ref":"google.ai.generativelanguage_v1beta.types.generative_service.GenerateContentRequest","kind":"Gdef","module_public":false},"GenerateContentResponse":{".class":"SymbolTableNode","cross_ref":"google.ai.generativelanguage_v1beta.types.generative_service.GenerateContentResponse","kind":"Gdef","module_public":false},"GenerateMessageRequest":{".class":"SymbolTableNode","cross_ref":"google.ai.generativelanguage_v1beta.types.discuss_service.GenerateMessageRequest","kind":"Gdef","module_public":false},"GenerateMessageResponse":{".class":"SymbolTableNode","cross_ref":"google.ai.generativelanguage_v1beta.types.discuss_service.GenerateMessageResponse","kind":"Gdef","module_public":false},"GenerateTextRequest":{".class":"SymbolTableNode","cross_ref":"google.ai.generativelanguage_v1beta.types.text_service.GenerateTextRequest","kind":"Gdef","module_public":false},"GenerateTextResponse":{".class":"SymbolTableNode","cross_ref":"google.ai.generativelanguage_v1beta.types.text_service.GenerateTextResponse","kind":"Gdef","module_public":false},"GenerationConfig":{".class":"SymbolTableNode","cross_ref":"google.ai.generativelanguage_v1beta.types.generative_service.GenerationConfig","kind":"Gdef","module_public":false},"GetCachedContentRequest":{".class":"SymbolTableNode","cross_ref":"google.ai.generativelanguage_v1beta.types.cache_service.GetCachedContentRequest","kind":"Gdef","module_public":false},"GetChunkRequest":{".class":"SymbolTableNode","cross_ref":"google.ai.generativelanguage_v1beta.types.retriever_service.GetChunkRequest","kind":"Gdef","module_public":false},"GetCorpusRequest":{".class":"SymbolTableNode","cross_ref":"google.ai.generativelanguage_v1beta.types.retriever_service.GetCorpusRequest","kind":"Gdef","module_public":false},"GetDocumentRequest":{".class":"SymbolTableNode","cross_ref":"google.ai.generativelanguage_v1beta.types.retriever_service.GetDocumentRequest","kind":"Gdef","module_public":false},"GetFileRequest":{".class":"SymbolTableNode","cross_ref":"google.ai.generativelanguage_v1beta.types.file_service.GetFileRequest","kind":"Gdef","module_public":false},"GetModelRequest":{".class":"SymbolTableNode","cross_ref":"google.ai.generativelanguage_v1beta.types.model_service.GetModelRequest","kind":"Gdef","module_public":false},"GetPermissionRequest":{".class":"SymbolTableNode","cross_ref":"google.ai.generativelanguage_v1beta.types.permission_service.GetPermissionRequest","kind":"Gdef","module_public":false},"GetTunedModelRequest":{".class":"SymbolTableNode","cross_ref":"google.ai.generativelanguage_v1beta.types.model_service.GetTunedModelRequest","kind":"Gdef","module_public":false},"GoogleSearchRetrieval":{".class":"SymbolTableNode","cross_ref":"google.ai.generativelanguage_v1beta.types.content.GoogleSearchRetrieval","kind":"Gdef","module_public":false},"GroundingAttribution":{".class":"SymbolTableNode","cross_ref":"google.ai.generativelanguage_v1beta.types.generative_service.GroundingAttribution","kind":"Gdef","module_public":false},"GroundingChunk":{".class":"SymbolTableNode","cross_ref":"google.ai.generativelanguage_v1beta.types.generative_service.GroundingChunk","kind":"Gdef","module_public":false},"GroundingMetadata":{".class":"SymbolTableNode","cross_ref":"google.ai.generativelanguage_v1beta.types.generative_service.GroundingMetadata","kind":"Gdef","module_public":false},"GroundingPassage":{".class":"SymbolTableNode","cross_ref":"google.ai.generativelanguage_v1beta.types.content.GroundingPassage","kind":"Gdef","module_public":false},"GroundingPassages":{".class":"SymbolTableNode","cross_ref":"google.ai.generativelanguage_v1beta.types.content.GroundingPassages","kind":"Gdef","module_public":false},"GroundingSupport":{".class":"SymbolTableNode","cross_ref":"google.ai.generativelanguage_v1beta.types.generative_service.GroundingSupport","kind":"Gdef","module_public":false},"HarmCategory":{".class":"SymbolTableNode","cross_ref":"google.ai.generativelanguage_v1beta.types.safety.HarmCategory","kind":"Gdef","module_public":false},"Hyperparameters":{".class":"SymbolTableNode","cross_ref":"google.ai.generativelanguage_v1beta.types.tuned_model.Hyperparameters","kind":"Gdef","module_public":false},"ListCachedContentsRequest":{".class":"SymbolTableNode","cross_ref":"google.ai.generativelanguage_v1beta.types.cache_service.ListCachedContentsRequest","kind":"Gdef","module_public":false},"ListCachedContentsResponse":{".class":"SymbolTableNode","cross_ref":"google.ai.generativelanguage_v1beta.types.cache_service.ListCachedContentsResponse","kind":"Gdef","module_public":false},"ListChunksRequest":{".class":"SymbolTableNode","cross_ref":"google.ai.generativelanguage_v1beta.types.retriever_service.ListChunksRequest","kind":"Gdef","module_public":false},"ListChunksResponse":{".class":"SymbolTableNode","cross_ref":"google.ai.generativelanguage_v1beta.types.retriever_service.ListChunksResponse","kind":"Gdef","module_public":false},"ListCorporaRequest":{".class":"SymbolTableNode","cross_ref":"google.ai.generativelanguage_v1beta.types.retriever_service.ListCorporaRequest","kind":"Gdef","module_public":false},"ListCorporaResponse":{".class":"SymbolTableNode","cross_ref":"google.ai.generativelanguage_v1beta.types.retriever_service.ListCorporaResponse","kind":"Gdef","module_public":false},"ListDocumentsRequest":{".class":"SymbolTableNode","cross_ref":"google.ai.generativelanguage_v1beta.types.retriever_service.ListDocumentsRequest","kind":"Gdef","module_public":false},"ListDocumentsResponse":{".class":"SymbolTableNode","cross_ref":"google.ai.generativelanguage_v1beta.types.retriever_service.ListDocumentsResponse","kind":"Gdef","module_public":false},"ListFilesRequest":{".class":"SymbolTableNode","cross_ref":"google.ai.generativelanguage_v1beta.types.file_service.ListFilesRequest","kind":"Gdef","module_public":false},"ListFilesResponse":{".class":"SymbolTableNode","cross_ref":"google.ai.generativelanguage_v1beta.types.file_service.ListFilesResponse","kind":"Gdef","module_public":false},"ListModelsRequest":{".class":"SymbolTableNode","cross_ref":"google.ai.generativelanguage_v1beta.types.model_service.ListModelsRequest","kind":"Gdef","module_public":false},"ListModelsResponse":{".class":"SymbolTableNode","cross_ref":"google.ai.generativelanguage_v1beta.types.model_service.ListModelsResponse","kind":"Gdef","module_public":false},"ListPermissionsRequest":{".class":"SymbolTableNode","cross_ref":"google.ai.generativelanguage_v1beta.types.permission_service.ListPermissionsRequest","kind":"Gdef","module_public":false},"ListPermissionsResponse":{".class":"SymbolTableNode","cross_ref":"google.ai.generativelanguage_v1beta.types.permission_service.ListPermissionsResponse","kind":"Gdef","module_public":false},"ListTunedModelsRequest":{".class":"SymbolTableNode","cross_ref":"google.ai.generativelanguage_v1beta.types.model_service.ListTunedModelsRequest","kind":"Gdef","module_public":false},"ListTunedModelsResponse":{".class":"SymbolTableNode","cross_ref":"google.ai.generativelanguage_v1beta.types.model_service.ListTunedModelsResponse","kind":"Gdef","module_public":false},"LogprobsResult":{".class":"SymbolTableNode","cross_ref":"google.ai.generativelanguage_v1beta.types.generative_service.LogprobsResult","kind":"Gdef","module_public":false},"Message":{".class":"SymbolTableNode","cross_ref":"google.ai.generativelanguage_v1beta.types.discuss_service.Message","kind":"Gdef","module_public":false},"MessagePrompt":{".class":"SymbolTableNode","cross_ref":"google.ai.generativelanguage_v1beta.types.discuss_service.MessagePrompt","kind":"Gdef","module_public":false},"MetadataFilter":{".class":"SymbolTableNode","cross_ref":"google.ai.generativelanguage_v1beta.types.retriever.MetadataFilter","kind":"Gdef","module_public":false},"Model":{".class":"SymbolTableNode","cross_ref":"google.ai.generativelanguage_v1beta.types.model.Model","kind":"Gdef","module_public":false},"Part":{".class":"SymbolTableNode","cross_ref":"google.ai.generativelanguage_v1beta.types.content.Part","kind":"Gdef","module_public":false},"Permission":{".class":"SymbolTableNode","cross_ref":"google.ai.generativelanguage_v1beta.types.permission.Permission","kind":"Gdef","module_public":false},"PrebuiltVoiceConfig":{".class":"SymbolTableNode","cross_ref":"google.ai.generativelanguage_v1beta.types.generative_service.PrebuiltVoiceConfig","kind":"Gdef","module_public":false},"PredictRequest":{".class":"SymbolTableNode","cross_ref":"google.ai.generativelanguage_v1beta.types.prediction_service.PredictRequest","kind":"Gdef","module_public":false},"PredictResponse":{".class":"SymbolTableNode","cross_ref":"google.ai.generativelanguage_v1beta.types.prediction_service.PredictResponse","kind":"Gdef","module_public":false},"QueryCorpusRequest":{".class":"SymbolTableNode","cross_ref":"google.ai.generativelanguage_v1beta.types.retriever_service.QueryCorpusRequest","kind":"Gdef","module_public":false},"QueryCorpusResponse":{".class":"SymbolTableNode","cross_ref":"google.ai.generativelanguage_v1beta.types.retriever_service.QueryCorpusResponse","kind":"Gdef","module_public":false},"QueryDocumentRequest":{".class":"SymbolTableNode","cross_ref":"google.ai.generativelanguage_v1beta.types.retriever_service.QueryDocumentRequest","kind":"Gdef","module_public":false},"QueryDocumentResponse":{".class":"SymbolTableNode","cross_ref":"google.ai.generativelanguage_v1beta.types.retriever_service.QueryDocumentResponse","kind":"Gdef","module_public":false},"RelevantChunk":{".class":"SymbolTableNode","cross_ref":"google.ai.generativelanguage_v1beta.types.retriever_service.RelevantChunk","kind":"Gdef","module_public":false},"RetrievalMetadata":{".class":"SymbolTableNode","cross_ref":"google.ai.generativelanguage_v1beta.types.generative_service.RetrievalMetadata","kind":"Gdef","module_public":false},"SafetyFeedback":{".class":"SymbolTableNode","cross_ref":"google.ai.generativelanguage_v1beta.types.safety.SafetyFeedback","kind":"Gdef","module_public":false},"SafetyRating":{".class":"SymbolTableNode","cross_ref":"google.ai.generativelanguage_v1beta.types.safety.SafetyRating","kind":"Gdef","module_public":false},"SafetySetting":{".class":"SymbolTableNode","cross_ref":"google.ai.generativelanguage_v1beta.types.safety.SafetySetting","kind":"Gdef","module_public":false},"Schema":{".class":"SymbolTableNode","cross_ref":"google.ai.generativelanguage_v1beta.types.content.Schema","kind":"Gdef","module_public":false},"SearchEntryPoint":{".class":"SymbolTableNode","cross_ref":"google.ai.generativelanguage_v1beta.types.generative_service.SearchEntryPoint","kind":"Gdef","module_public":false},"Segment":{".class":"SymbolTableNode","cross_ref":"google.ai.generativelanguage_v1beta.types.generative_service.Segment","kind":"Gdef","module_public":false},"SemanticRetrieverConfig":{".class":"SymbolTableNode","cross_ref":"google.ai.generativelanguage_v1beta.types.generative_service.SemanticRetrieverConfig","kind":"Gdef","module_public":false},"SpeechConfig":{".class":"SymbolTableNode","cross_ref":"google.ai.generativelanguage_v1beta.types.generative_service.SpeechConfig","kind":"Gdef","module_public":false},"StringList":{".class":"SymbolTableNode","cross_ref":"google.ai.generativelanguage_v1beta.types.retriever.StringList","kind":"Gdef","module_public":false},"TaskType":{".class":"SymbolTableNode","cross_ref":"google.ai.generativelanguage_v1beta.types.generative_service.TaskType","kind":"Gdef","module_public":false},"TextCompletion":{".class":"SymbolTableNode","cross_ref":"google.ai.generativelanguage_v1beta.types.text_service.TextCompletion","kind":"Gdef","module_public":false},"TextPrompt":{".class":"SymbolTableNode","cross_ref":"google.ai.generativelanguage_v1beta.types.text_service.TextPrompt","kind":"Gdef","module_public":false},"Tool":{".class":"SymbolTableNode","cross_ref":"google.ai.generativelanguage_v1beta.types.content.Tool","kind":"Gdef","module_public":false},"ToolConfig":{".class":"SymbolTableNode","cross_ref":"google.ai.generativelanguage_v1beta.types.content.ToolConfig","kind":"Gdef","module_public":false},"TransferOwnershipRequest":{".class":"SymbolTableNode","cross_ref":"google.ai.generativelanguage_v1beta.types.permission_service.TransferOwnershipRequest","kind":"Gdef","module_public":false},"TransferOwnershipResponse":{".class":"SymbolTableNode","cross_ref":"google.ai.generativelanguage_v1beta.types.permission_service.TransferOwnershipResponse","kind":"Gdef","module_public":false},"TunedModel":{".class":"SymbolTableNode","cross_ref":"google.ai.generativelanguage_v1beta.types.tuned_model.TunedModel","kind":"Gdef","module_public":false},"TunedModelSource":{".class":"SymbolTableNode","cross_ref":"google.ai.generativelanguage_v1beta.types.tuned_model.TunedModelSource","kind":"Gdef","module_public":false},"TuningExample":{".class":"SymbolTableNode","cross_ref":"google.ai.generativelanguage_v1beta.types.tuned_model.TuningExample","kind":"Gdef","module_public":false},"TuningExamples":{".class":"SymbolTableNode","cross_ref":"google.ai.generativelanguage_v1beta.types.tuned_model.TuningExamples","kind":"Gdef","module_public":false},"TuningSnapshot":{".class":"SymbolTableNode","cross_ref":"google.ai.generativelanguage_v1beta.types.tuned_model.TuningSnapshot","kind":"Gdef","module_public":false},"TuningTask":{".class":"SymbolTableNode","cross_ref":"google.ai.generativelanguage_v1beta.types.tuned_model.TuningTask","kind":"Gdef","module_public":false},"Type":{".class":"SymbolTableNode","cross_ref":"google.ai.generativelanguage_v1beta.types.content.Type","kind":"Gdef","module_public":false},"UpdateCachedContentRequest":{".class":"SymbolTableNode","cross_ref":"google.ai.generativelanguage_v1beta.types.cache_service.UpdateCachedContentRequest","kind":"Gdef","module_public":false},"UpdateChunkRequest":{".class":"SymbolTableNode","cross_ref":"google.ai.generativelanguage_v1beta.types.retriever_service.UpdateChunkRequest","kind":"Gdef","module_public":false},"UpdateCorpusRequest":{".class":"SymbolTableNode","cross_ref":"google.ai.generativelanguage_v1beta.types.retriever_service.UpdateCorpusRequest","kind":"Gdef","module_public":false},"UpdateDocumentRequest":{".class":"SymbolTableNode","cross_ref":"google.ai.generativelanguage_v1beta.types.retriever_service.UpdateDocumentRequest","kind":"Gdef","module_public":false},"UpdatePermissionRequest":{".class":"SymbolTableNode","cross_ref":"google.ai.generativelanguage_v1beta.types.permission_service.UpdatePermissionRequest","kind":"Gdef","module_public":false},"UpdateTunedModelRequest":{".class":"SymbolTableNode","cross_ref":"google.ai.generativelanguage_v1beta.types.model_service.UpdateTunedModelRequest","kind":"Gdef","module_public":false},"VideoMetadata":{".class":"SymbolTableNode","cross_ref":"google.ai.generativelanguage_v1beta.types.file.VideoMetadata","kind":"Gdef","module_public":false},"VoiceConfig":{".class":"SymbolTableNode","cross_ref":"google.ai.generativelanguage_v1beta.types.generative_service.VoiceConfig","kind":"Gdef","module_public":false},"__all__":{".class":"SymbolTableNode","cross_ref":"google.ai.generativelanguage_v1beta.types.__all__","kind":"Gdef","module_public":false},"__annotations__":{".class":"SymbolTableNode","kind":"Gdef","module_public":false,"node":{".class":"Var","flags":["is_ready"],"fullname":"google.generativeai.protos.__annotations__","name":"__annotations__","type":{".class":"Instance","args":["builtins.str",{".class":"AnyType","missing_import_name":null,"source_any":null,"type_of_any":6}],"extra_attrs":null,"type_ref":"builtins.dict"}}},"__doc__":{".class":"SymbolTableNode","kind":"Gdef","module_public":false,"node":{".class":"Var","flags":["is_ready"],"fullname":"google.generativeai.protos.__doc__","name":"__doc__","type":"builtins.str"}},"__file__":{".class":"SymbolTableNode","kind":"Gdef","module_public":false,"node":{".class":"Var","flags":["is_ready"],"fullname":"google.generativeai.protos.__file__","name":"__file__","type":"builtins.str"}},"__name__":{".class":"SymbolTableNode","kind":"Gdef","module_public":false,"node":{".class":"Var","flags":["is_ready"],"fullname":"google.generativeai.protos.__name__","name":"__name__","type":"builtins.str"}},"__package__":{".class":"SymbolTableNode","kind":"Gdef","module_public":false,"node":{".class":"Var","flags":["is_ready"],"fullname":"google.generativeai.protos.__package__","name":"__package__","type":"builtins.str"}},"__spec__":{".class":"SymbolTableNode","kind":"Gdef","module_public":false,"node":{".class":"Var","flags":["is_ready"],"fullname":"google.generativeai.protos.__spec__","name":"__spec__","type":"_frozen_importlib.ModuleSpec"}}},"path":"C:\\Users\\user\\AppData\\Local\\Packages\\PythonSoftwareFoundation.Python.3.12_qbz5n2kfra8p0\\LocalCache\\local-packages\\Python312\\site-packages\\google\\generativeai\\protos.py"}